debloat/__init__.py
debloat/auxiliary.py
debloat/gui.py
debloat/main.py
debloat/performanceTest.py
debloat/processor.py
debloat/processor.pyi
debloat/hook/hook-tkinterdnd2.py
debloat/temp/temp_exports.py
debloat/temp/temp_parseRDATA.py
debloat/temp/temp_scannull.py
debloat/tests/__init__.py
debloat/tests/debloat_test.py
debloat/utilities/__init__.py
debloat/utilities/nsisParser.py
debloat/utilities/pyflate.py
debloat/utilities/readers.py
debloat/utilities/rsrc.py
debloat-1.6.5.dist-info/licenses/LICENSE
debloat-1.6.5.dist-info/METADATA
debloat-1.6.5.dist-info/WHEEL
debloat-1.6.5.dist-info/entry_points.txt
debloat-1.6.5.dist-info/top_level.txt
debloat-1.6.5.dist-info/RECORD
