Metadata-Version: 2.4
Name: debloat
Version: 1.6.5
Summary: Debloat is an tool to remove excess garbage from bloated executables.
Author-email: Squiblydoo <Squiblydoo@pm.me>
Project-URL: Homepage, https://github.com/Squiblydoo/debloat
Project-URL: Bug Tracker, https://github.com/Squiblydoo/debloat/issues
Classifier: Programming Language :: Python :: 3
Classifier: License :: OSI Approved :: BSD License
Classifier: Operating System :: OS Independent
Requires-Python: >=3.6
License-File: LICENSE
Requires-Dist: tkinterdnd2>=0.3.0
Requires-Dist: pefile>=2023.2.0
Dynamic: license-file
